babel-stubs/METADATA.toml
babel-stubs/__init__.pyi
babel-stubs/core.pyi
babel-stubs/dates.pyi
babel-stubs/languages.pyi
babel-stubs/lists.pyi
babel-stubs/localedata.pyi
babel-stubs/numbers.pyi
babel-stubs/plural.pyi
babel-stubs/support.pyi
babel-stubs/units.pyi
babel-stubs/util.pyi
babel-stubs/localtime/__init__.pyi
babel-stubs/localtime/_unix.pyi
babel-stubs/localtime/_win32.pyi
babel-stubs/messages/__init__.pyi
babel-stubs/messages/catalog.pyi
babel-stubs/messages/checkers.pyi
babel-stubs/messages/extract.pyi
babel-stubs/messages/frontend.pyi
babel-stubs/messages/jslexer.pyi
babel-stubs/messages/mofile.pyi
babel-stubs/messages/plurals.pyi
babel-stubs/messages/pofile.pyi
types_babel-2.11.0.15.dist-info/METADATA
types_babel-2.11.0.15.dist-info/WHEEL
types_babel-2.11.0.15.dist-info/top_level.txt
types_babel-2.11.0.15.dist-info/RECORD
